setup.py
everstdin/__init__.py
everstdin/config.py
everstdin/everstdin.py
everstdin.egg-info/PKG-INFO
everstdin.egg-info/SOURCES.txt
everstdin.egg-info/dependency_links.txt
everstdin.egg-info/entry_points.txt
everstdin.egg-info/requires.txt
everstdin.egg-info/top_level.txt