Metadata-Version: 1.0
Name: everstdin
Version: 0.7
Summary: Evernote command line tool
Home-page: https://github.com/ngc224/everstdin
Author: Yoshihiko Nishida
Author-email: nishida@ngc224.org
License: UNKNOWN
Platform: UNKNOWN
